odoo/addons/mail_attach_existing_attachment_account/README.rst
odoo/addons/mail_attach_existing_attachment_account/__init__.py
odoo/addons/mail_attach_existing_attachment_account/__manifest__.py
odoo/addons/mail_attach_existing_attachment_account/i18n/mail_attach_existing_attachment_account.pot
odoo/addons/mail_attach_existing_attachment_account/readme/CONTRIBUTORS.rst
odoo/addons/mail_attach_existing_attachment_account/readme/DESCRIPTION.rst
odoo/addons/mail_attach_existing_attachment_account/static/description/icon.png
odoo/addons/mail_attach_existing_attachment_account/static/description/index.html
odoo/addons/mail_attach_existing_attachment_account/tests/__init__.py
odoo/addons/mail_attach_existing_attachment_account/tests/test_mail_attach_existing_attachment_account.py
odoo/addons/mail_attach_existing_attachment_account/wizard/__init__.py
odoo/addons/mail_attach_existing_attachment_account/wizard/account_invoice_send.py
odoo/addons/mail_attach_existing_attachment_account/wizard/account_invoice_send_view.xml
odoo13_addon_mail_attach_existing_attachment_account-13.0.1.0.1.dev3.dist-info/METADATA
odoo13_addon_mail_attach_existing_attachment_account-13.0.1.0.1.dev3.dist-info/WHEEL
odoo13_addon_mail_attach_existing_attachment_account-13.0.1.0.1.dev3.dist-info/top_level.txt
odoo13_addon_mail_attach_existing_attachment_account-13.0.1.0.1.dev3.dist-info/RECORD
